LICENSE
MANIFEST.in
README.rst
setup.py
django_cukierpuder_jwt_auth.egg-info/PKG-INFO
django_cukierpuder_jwt_auth.egg-info/SOURCES.txt
django_cukierpuder_jwt_auth.egg-info/dependency_links.txt
django_cukierpuder_jwt_auth.egg-info/requires.txt
django_cukierpuder_jwt_auth.egg-info/top_level.txt
jwt_auth/__init__.py
jwt_auth/admin.py
jwt_auth/apps.py
jwt_auth/models.py
jwt_auth/serializers.py
jwt_auth/tests.py
jwt_auth/urls.py
jwt_auth/views.py