Metadata-Version: 1.1
Name: django-cukierpuder-jwt-auth
Version: 0.2
Summary: A simple authorization Django app based on JSON Web Tokens.
Home-page: https://github.com/CukierPuder/django-cukierpuder-jwt-auth
Author: CukierPuder
Author-email: cukier_puder@hotmail.com
License: GNU
Download-URL: https://github.com/CukierPuder/django-cukierpuder-jwt-auth/archive/v0.2.tar.gz
Platform: UNKNOWN
Classifier: Environment :: Web Environment
Classifier: Framework :: Django
Classifier: Framework :: Django :: 2.1
Classifier: Intended Audience :: Developers
Classifier: License :: OSI Approved :: GNU General Public License (GPL)
Classifier: Operating System :: OS Independent
Classifier: Programming Language :: Python
Classifier: Programming Language :: Python :: 3.6
Classifier: Programming Language :: Python :: 3.7
Classifier: Topic :: Internet :: WWW/HTTP
